{
  "ADAPTIVEENCRYPTORS" : "Adaptive Encryptors Capture",
  "ARCHIVEDEMISSIONDATA": "Irregular Emission Data",
  "BULKSCANDATA": "Anomalous Bulk Scan Data",
  "CLASSIFIEDSCANDATA" : "Classified Scan Fragment",
  "COMPACTEMISSIONSDATA": "Abnormal Compact Emissions Data",
  "CONSUMERFIRMWARE": "Modified Consumer Firmware",
  "DATAMINEDWAKE": "Datamined Wake Exceptions",
  "DECODEDEMISSIONDATA": "Decoded Emission Data",
  "DISRUPTEDWAKEECHOES": "Atypical Disrupted Wake Echoes",
  "EMBEDDEDFIRMWARE": "Modified Embedded Firmware",
  "EMISSIONDATA": "Unexpected Emission Data",
  "ENCODEDSCANDATA": "Divergent Scan Data",
  "ENCRYPTEDFILES" : "Unusual Encrypted Files",
  "ENCRYPTIONARCHIVES" : "Atypical Encryption Archives",
  "ENCRYPTIONCODES": "Tagged Encryption Codes",
  "FSDTELEMETRY": "Anomalous FSD Telemetry",
  "HYPERSPACETRAJECTORIES" : "Eccentric Hyperspace Trajectories",
  "INDUSTRIALFIRMWARE": "Cracked Industrial Firmware",
  "LEGACYFIRMWARE": "Specialised Legacy Firmware",
  "SCANARCHIVES": "Unidentified Scan Archives",
  "SCANDATABANKS": "Classified Scan Databanks",
  "SCRAMBLEDEMISSIONDATA": "Exceptional Scrambled Emission Data",
  "SECURITYFIRMWARE" : "Security Firmware Patch",
  "SHIELDCYCLERECORDINGS": "Distorted Shield Cycle Recordings",
  "SHIELDDENSITYREPORTS": "Untypical Shield Scans ",
  "SHIELDFREQUENCYDATA": "Peculiar Shield Frequency Data",
  "SHIELDPATTERNANALYSIS": "Aberrant Shield Pattern Analysis",
  "SHIELDSOAKANALYSIS": "Inconsistent Shield Soak Analysis",
  "SYMMETRICKEYS" : "Open Symmetric Keys",
  "WAKESOLUTIONS": "Strange Wake Solutions",

  "BASICCONDUCTORS" : "Basic Conductors",
  "BIOTECHCONDUCTORS" : "Biotech Conductors",
  "CHEMICALDISTILLERY" : "Chemical Distillery",
  "CHEMICALMANIPULATORS" : "Chemical Manipulators",
  "CHEMICALPROCESSORS" : "Chemical Processors",
  "CHEMICALSTORAGEUNITS" : "Chemical Storage Units",
  "COMPACTCOMPOSITES" : "Compact Composites",
  "COMPOUNDSHIELDING" : "Compound Shielding",
  "CONDUCTIVECERAMICS" : "Conductive Ceramics",
  "CONDUCTIVECOMPONENTS" : "Conductive Components",
  "CONDUCTIVEPOLYMERS" : "Conductive Polymers",
  "CONFIGURABLECOMPONENTS" : "Configurable Components",
  "CRYSTALSHARDS" : "Crystal Shards",
  "ELECTROCHEMICALARRAYS" : "Electrochemical Arrays",
  "EXQUISITEFOCUSCRYSTALS" : "Exquisite Focus Crystals",
  "FEDCORECOMPOSITES" : "Core Dynamics Composites",
  "FEDPROPRIETARYCOMPOSITES" : "Proprietary Composites",
  "FILAMENTCOMPOSITES" : "Filament Composites",
  "FOCUSCRYSTALS" : "Focus Crystals",
  "GALVANISINGALLOYS" : "Galvanising Alloys",
  "GRIDRESISTORS" : "Grid Resistors",
  "HEATCONDUCTIONWIRING" : "Heat Conduction Wiring",
  "HEATDISPERSIONPLATE" : "Heat Dispersion Plate",
  "HEATEXCHANGERS" : "Heat Exchangers",
  "HEATRESISTANTCERAMICS" : "Heat Resistant Ceramics",
  "HEATVANES" : "Heat Vanes",
  "HIGHDENSITYCOMPOSITES" : "High Density Composites",
  "HYBRIDCAPACITORS" : "Hybrid Capacitors",
  "IMPERIALSHIELDING" : "Imperial Shielding",
  "IMPROVISEDCOMPONENTS" : "Improvised Components",
  "MECHANICALCOMPONENTS" : "Mechanical Components",
  "MECHANICALEQUIPMENT" : "Mechanical Equipment",
  "MECHANICALSCRAP" : "Mechanical Scrap",
  "MILITARYGRADEALLOYS" : "Military Grade Alloys",
  "MILITARYSUPERCAPACITORS" : "Military Supercapacitors",
  "PHARMACEUTICALISOLATORS" : "Pharmaceutical Isolators",
  "PHASEALLOYS" : "Phase Alloys",
  "POLYMERCAPACITORS" : "Polymer Capacitors",
  "PRECIPITATEDALLOYS" : "Precipitated Alloys",
  "PROTOHEATRADIATORS" : "Proto Heat Radiators",
  "PROTOLIGHTALLOYS" : "Proto Light Alloys",
  "PROTORADIOLICALLOYS" : "Proto Radiolic Alloys",
  "REFINEDFOCUSCRYSTALS" : "Refined Focus Crystals",
  "SALVAGEDALLOYS" : "Salvaged Alloys",
  "SHIELDEMITTERS" : "Shield Emitters",
  "SHIELDINGSENSORS" : "Shielding Sensors",
  "TEMPEREDALLOYS" : "Tempered Alloys",
  "THERMICALLOYS" : "Thermic Alloys",
  "UNCUTFOCUSCRYSTALS" : "Flawed Focus Crystals",
  "WORNSHIELDEMITTERS" : "Worn Shield Emitters",

  "ANTIMONY" : "Antimony (Sb)",
  "ARSENIC" : "Arsenic (As)",
  "BORON" : "Boron (B)",
  "CADMIUM" : "Cadmium (Cd)",
  "CARBON" : "Carbon (C)",
  "CHROMIUM" : "Chromium (Cr)",
  "GERMANIUM" : "Germanium (Ge)",
  "IRON" : "Iron (Fe)",
  "LEAD" : "Lead (Pb)",
  "MANGANESE" : "Manganese (Mn)",
  "MERCURY" : "Mercury (Hg)",
  "MOLYBDENUM" : "Molybdenum (Mo)",
  "NICKEL" : "Nickel (Ni)",
  "NIOBIUM" : "Niobium (Nb)",
  "PHOSPHORUS" : "Phosphorus (P)",
  "POLONIUM" : "Polonium (Po)",
  "RHENIUM" : "Rhenium (Re)",
  "RUTHENIUM" : "Ruthenium (Ru)",
  "SELENIUM" : "Selenium (Se)",
  "SULPHUR" : "Sulphur (S)",
  "TECHNETIUM" : "Technetium (Tc)",
  "TELLURIUM" : "Tellurium (Te)",
  "TIN" : "Tin (Sn)",
  "TUNGSTEN" : "Tungsten (W)",
  "VANADIUM" : "Vanadium (V)",
  "YTTRIUM" : "Yttrium (Y)",
  "ZINC" : "Zinc (Zn)",
  "ZIRCONIUM" : "Zirconium (Zr)"
}